gpw/__init__.py
gpw/app.py
gpw_faisalgh-0.1.0.dist-info/METADATA
gpw_faisalgh-0.1.0.dist-info/WHEEL
gpw_faisalgh-0.1.0.dist-info/RECORD
