Metadata-Version: 2.3
Name: gpw-faisalgh
Version: 0.1.0
Summary: 
Author: faisalgh
Author-email: faisalgh06@gmail.com
Requires-Python: >=3.13,<4.0
Classifier: Programming Language :: Python :: 3
Classifier: Programming Language :: Python :: 3.13
Requires-Dist: flask (==3.0.0)
Requires-Dist: langchain-ollama (==0.1.0)
Requires-Dist: requests (>=2.32.3,<3.0.0)
